randaugment/__init__.py
randaugment/randaugment.py
randaugment-1.0.2.dist-info/LICENSE
randaugment-1.0.2.dist-info/METADATA
randaugment-1.0.2.dist-info/WHEEL
randaugment-1.0.2.dist-info/top_level.txt
randaugment-1.0.2.dist-info/RECORD
