Metadata-Version: 2.1
Name: randaugment
Version: 1.0.2
Summary: UNKNOWN
Home-page: https://github.com/jizongFox/pytorch-randaugment
Author: Jizong Peng
Author-email: jizong.peng.1@etsmtl.net
License: MIT
Platform: UNKNOWN
Classifier: License :: OSI Approved :: MIT License
Classifier: Programming Language :: Python :: 3
Classifier: Programming Language :: Python :: 3.7
